neqsim/__init__.py
neqsim/lib/java11/neqsim-3.3.0.jar
neqsim/lib/java8/neqsim-3.3.0-Java8.jar
neqsim/neqsimpython.py
neqsim/process/__init__.py
neqsim/process/measurement.py
neqsim/process/processTools.py
neqsim/process/unitop.py
neqsim/py.typed
neqsim/standards/__init__.py
neqsim/standards/standardTools.py
neqsim/thermo/__init__.py
neqsim/thermo/thermoTools.py
neqsim-3.3.0.dist-info/METADATA
neqsim-3.3.0.dist-info/WHEEL
neqsim-3.3.0.dist-info/licenses/LICENSE
neqsim-3.3.0.dist-info/RECORD
