Metadata-Version: 2.4
Name: neqsim
Version: 3.3.0
Summary: NeqSim is a tool for thermodynamic and process calculations
License: Apache-2.0
License-File: LICENSE
Author: Even Solbraa
Author-email: esolbraa@gmail.com
Requires-Python: >=3.9,<4.0
Classifier: License :: OSI Approved :: Apache Software License
Classifier: Operating System :: OS Independent
Classifier: Programming Language :: Python :: 3
Classifier: Programming Language :: Python :: 3.9
Classifier: Programming Language :: Python :: 3.10
Classifier: Programming Language :: Python :: 3.11
Classifier: Programming Language :: Python :: 3.12
Classifier: Programming Language :: Python :: 3.13
Classifier: Programming Language :: Python :: 3.14
Provides-Extra: interactive
Requires-Dist: JPype1 (>=1.5.0,<2.0.0)
Requires-Dist: jupyter (>=1.0.0,<2.0.0) ; extra == "interactive"
Requires-Dist: matplotlib (>=3.7.0,<4.0.0) ; extra == "interactive"
Requires-Dist: numpy (>1.25.2)
Requires-Dist: pandas (>=2.0.3,<3.0.0)
Requires-Dist: tabulate (>=0.9.0,<0.10.0) ; extra == "interactive"
Project-URL: Homepage, https://github.com/Equinor/neqsim-python
Project-URL: Repository, https://github.com/Equinor/neqsim-python
